Traffic/FinalTransferSys.py
Traffic/NearStation.py
Traffic/ShuttleTimeGo.py
Traffic/SpanTime.py
Traffic/SubDIct.py
Traffic/SubTime.py
Traffic/SuttleDict.py
Traffic/__init__.py
Util/Eclass.py
Util/Gpss.py
Util/__init__.py
Weather/KorWeather.py
Weather/KorWeather_RainData.py
Weather/NaverWeather.py
Weather/OpenWeather.py
Weather/OpenWeather_ImgFile.py
Weather/VisualCrossing.py
Weather/WeatherZip.py
Weather/Weather_Test_Data.py
Weather/__init__.py
ToBi_pkg-0.0.1.dist-info/LICENSE
ToBi_pkg-0.0.1.dist-info/METADATA
ToBi_pkg-0.0.1.dist-info/WHEEL
ToBi_pkg-0.0.1.dist-info/top_level.txt
ToBi_pkg-0.0.1.dist-info/RECORD
