Metadata-Version: 2.1
Name: ToBi-pkg
Version: 0.0.1
Summary: A package for KPU_ToBi
Home-page: https://github.com/golapaduck
Author: KPU_ToBi
Author-email: golapaduck29@naver.com
License: UNKNOWN
Platform: UNKNOWN
Classifier: Programming Language :: Python :: 3.8
